basic_instagram_library/__init__.py
basic_instagram_library/find_tags.py
basic_instagram_library/tests.py
basic_instagram_library-0.0.1.dist-info/LICENSE
basic_instagram_library-0.0.1.dist-info/METADATA
basic_instagram_library-0.0.1.dist-info/WHEEL
basic_instagram_library-0.0.1.dist-info/top_level.txt
basic_instagram_library-0.0.1.dist-info/RECORD
