Metadata-Version: 2.1
Name: basic-instagram-library
Version: 0.0.1
Summary: A library to read an instagram users tags
Home-page: https://github.com/holdenk/distributedcomputing4kids/code/basic_instagram_library
Author: Holden Karau
Author-email: holden@pigscanfly.ca
License: LICENSE
Platform: UNKNOWN
Requires-Dist: instagram-scraper (==1.6.1)
